{
  "chapters": 15,
  "levels": {
    "1": [
      {
        "question": "యెరూషలేములోని యూదులు ఎవరికి శుభములిఖించిరి?",
        "options": [
          "గ్రీకులకు",
          "రోమీయులకు",
          "ఐగుప్తులోని యూదులకు",
          "సిరియనులకు"
        ],
        "correct": 2
      },
      {
        "question": "దేవుడు మీకు దేనిని అనుగ్రహించును గాక?",
        "options": [
          "శాంతి (సమాధానము)",
          "అధికారము",
          "భూమి",
          "ధనము"
        ],
        "correct": 0
      },
      {
        "question": "పర్షియాలో నానీ గుడిలో ఎవరు చంపబడిరి?",
        "options": [
          "ప్రవక్తలు",
          "సైనికులు",
          "అంతియొకస్ రాజు",
          "యాజకులు"
        ],
        "correct": 2
      },
      {
        "question": "నెహెమ్యా అగ్నిని ఎక్కడి నుండి తీసెను?",
        "options": [
          "బలిపీఠము నుండి",
          "లోతైన బావి (గుంట) నుండి",
          "ఆకాశము నుండి",
          "నది నుండి"
        ],
        "correct": 1
      },
      {
        "question": "ఆ అగ్నిని ఏమని పిలిచిరి?",
        "options": [
          "బలి అగ్ని",
          "పరిశుద్ధాగ్ని",
          "దేవుని అగ్ని",
          "నెఫ్తార్"
        ],
        "correct": 3
      }
    ],
    "2": [
      {
        "question": "యిర్మీయా ప్రవక్త గుడారమును మందసమును ఎక్కడ దాచెను?",
        "options": [
          "యెరూషలేములో",
          "బబులోనులో",
          "దేవాలయములో",
          "మోషే ఎెక్కిన కొండ గుహలో"
        ],
        "correct": 3
      },
      {
        "question": "ఆ స్థలము ఎప్పుడు తెలియబడును?",
        "options": [
          "రాజు వచ్చినప్పుడు",
          "ఎప్పటికీ తెలియదు",
          "దేవుడు ప్రజలను సమకూర్చినప్పుడు",
          "యుద్ధము ముగిసినప్పుడు"
        ],
        "correct": 2
      },
      {
        "question": "సొలొమోను ఎన్ని రోజులు పండుగ ఆచరించెను?",
        "options": [
          "8",
          "3",
          "7",
          "12"
        ],
        "correct": 0
      },
      {
        "question": "గ్రంథాలయాన్ని ఎవరు స్థాపించిరి?",
        "options": [
          "సొలొమోను",
          "నెహెమ్యా",
          "యూదా",
          "యిర్మీయా"
        ],
        "correct": 1
      },
      {
        "question": "ఈ గ్రంథము (2 మక్కబీలు) ఎవరి చరిత్రను సంక్షిప్తముగా చెప్పుచున్నది?",
        "options": [
          "కైరేనీయుడైన జాసన్",
          "మోషే",
          "సొలొమోను",
          "దావీదు"
        ],
        "correct": 0
      }
    ],
    "3": [
      {
        "question": "ప్రధాన యాజకుడైన ఓనియాస్ కాలంలో పట్టణము ఎలా ఉండెను?",
        "options": [
          "కరువుతో",
          "భయముతో",
          "కలహములతో",
          "పూర్ణ శాంతితో"
        ],
        "correct": 3
      },
      {
        "question": "సీమోను దేవాలయ ధనమును గూర్చి ఎవరికి చెప్పెను?",
        "options": [
          "అపొల్లోనియస్ కు",
          "రాజుకు",
          "ఓనియాస్ కు",
          "ప్రజలకు"
        ],
        "correct": 0
      },
      {
        "question": "హేలియోడోరస్ ఎందుకు వచ్చెను?",
        "options": [
          "దర్శించుటకు",
          "ధనమును తీసుకొనిపోవుటకు",
          "బలి అర్పించుటకు",
          "ప్రార్థించుటకు"
        ],
        "correct": 1
      },
      {
        "question": "హేలియోడోరస్ కు ఎవరు కనబడిరి?",
        "options": [
          "రాజు",
          "యాజకుడు",
          "సైనికులు",
          "భయంకరమైన గుర్రపు రౌతు మరియు ఇద్దరు యవ్వనస్థులు"
        ],
        "correct": 3
      },
      {
        "question": "హేలియోడోరస్ ఎవరి ప్రార్థన వలన బ్రతికెను?",
        "options": [
          "సీమోను",
          "ప్రజలు",
          "ఓనియాస్",
          "రాజు"
        ],
        "correct": 2
      }
    ],
    "4": [
      {
        "question": "ఓనియాస్ సహోదరుడైన జాసన్ రాజుకు ఏమి లంచము ఇచ్చెను?",
        "options": [
          "భూమి",
          "బంగారము",
          "వెండి",
          "పశువులు"
        ],
        "correct": 2
      },
      {
        "question": "జాసన్ యెరూషలేములో ఏ ఆచారాలను ప్రవేశపెట్టెను?",
        "options": [
          "రోమా ఆచారాలు",
          "యూదుల ఆచారాలు",
          "గ్రీకు ఆచారాలు",
          "ఐగుప్తు ఆచారాలు"
        ],
        "correct": 2
      },
      {
        "question": "యాజకులు బలిపీఠమును విడిచి ఎక్కడికి వెళ్ళుచుండిరి?",
        "options": [
          "మల్లయుద్ధశాలకు (వ్యాయామశాలకు)",
          "ఇంటికి",
          "పొలమునకు",
          "యుద్ధానికి"
        ],
        "correct": 0
      },
      {
        "question": "జాసన్ తరువాత ఎవరు ప్రధాన యాజకత్వమును కొనుక్కొనెను?",
        "options": [
          "యూదా",
          "ఎలియాజరు",
          "మెనెలాస్",
          "సీమోను"
        ],
        "correct": 2
      },
      {
        "question": "ఓనియాస్ ఎక్కడ చంపబడెను?",
        "options": [
          "యెరూషలేములో",
          "దఫ్నే శరణాలయములో",
          "ఐగుప్తులో",
          "రోమ్ లో"
        ],
        "correct": 1
      }
    ],
    "5": [
      {
        "question": "యెరూషలేము ఆకాశంలో ఏమి కనబడెను?",
        "options": [
          "అగ్ని",
          "బంగారు రౌతులు మరియు సైన్యములు",
          "మేఘము",
          "నక్షత్రము"
        ],
        "correct": 1
      },
      {
        "question": "జాసన్ ఎంతమందిని చంపి పారిపోయెను?",
        "options": [
          "వంద",
          "స్వంత ప్రజలను",
          "శత్రువులను",
          "వెయ్యి"
        ],
        "correct": 1
      },
      {
        "question": "అంతియొకస్ దేవాలయములో నుండి వేటిని తీసుకొనిపోయెను?",
        "options": [
          "రాళ్లను",
          "నీళ్లను",
          "బలిపీఠము, దీపవృక్షము, పాత్రలు",
          "వస్త్రములను"
        ],
        "correct": 2
      },
      {
        "question": "యూదా మక్కబీ ఎక్కడికి పారిపోయెను?",
        "options": [
          "సముద్రమునకు",
          "అరణ్యమునకు",
          "ఐగుప్తుకు",
          "గలిలయకు"
        ],
        "correct": 1
      },
      {
        "question": "అంతియొకస్ ఎవరిని అధికారిగా నియమించెను?",
        "options": [
          "జాసన్ ను",
          "ఫిలిప్పును",
          "యూదాను",
          "ఓనియాస్ ను"
        ],
        "correct": 1
      }
    ],
    "6": [
      {
        "question": "యూదులు ఏ పండుగను ఆచరించకూడదని ఆజ్ఞాపించిరి?",
        "options": [
          "విశ్రాంతి దినము",
          "పర్ణశాలల పండుగ",
          "ఏదీ ఆచరించకూడదు",
          "పస్కా"
        ],
        "correct": 2
      },
      {
        "question": "గుహలో దాగియున్న వారిని ఏమి చేసిరి?",
        "options": [
          "చెరసాలలో వేసిరి",
          "వెళ్లగొట్టిరి",
          "విడిచిపెట్టిరి",
          "కాల్చి చంపిరి"
        ],
        "correct": 3
      },
      {
        "question": "ఎలియాజరు వయస్సు ఎంత?",
        "options": [
          "60",
          "70",
          "80",
          "90"
        ],
        "correct": 3
      },
      {
        "question": "ఎలియాజరును ఏమి తినమని బలవంతము చేసిరి?",
        "options": [
          "పండ్లు",
          "పంది మాంసము",
          "రొట్టె",
          "గొర్రె మాంసము"
        ],
        "correct": 1
      },
      {
        "question": "ఎలియాజరు దేనిని కోరుకొనెను?",
        "options": [
          "జీవితమును",
          "ధనమును",
          "పదవిని",
          "గౌరవప్రదమైన మరణమును"
        ],
        "correct": 3
      }
    ],
    "7": [
      {
        "question": "ఎంతమంది సహోదరులు పట్టుబడెను?",
        "options": [
          "ఐదుగురు",
          "పదిమంది",
          "ముగ్గురు",
          "ఏడుగురు"
        ],
        "correct": 3
      },
      {
        "question": "తల్లి తన కుమారులను ఎలా ధైర్యపరిచెను?",
        "options": [
          "గ్రీకు భాషలో",
          "ఏడ్చుచు",
          "స్వభాషలో (మాతృభాషలో)",
          "మౌనముగా"
        ],
        "correct": 2
      },
      {
        "question": "రెండవ వాడు చనిపోవుచు రాజుతో ఏమనెను?",
        "options": [
          "క్షమించుము",
          "నన్ను విడిచిపెట్టుము",
          "లోక రాజు మమ్మును తిరిగి లేపును",
          "నేను భయపడుచున్నాను"
        ],
        "correct": 2
      },
      {
        "question": "చివరిగా ఎవరు మరణించిరి?",
        "options": [
          "తల్లి",
          "సేవకుడు",
          "రాజు",
          "తండ్రి"
        ],
        "correct": 0
      },
      {
        "question": "వారు దేనిని బట్టి నిరీక్షణ కలిగిరి?",
        "options": [
          "కీర్తి",
          "రాజ్యము",
          "పునరుత్థానము",
          "ధనము"
        ],
        "correct": 2
      }
    ],
    "8": [
      {
        "question": "యూదా మక్కబీ ఎంతమందిని సమకూర్చుకొనెను?",
        "options": [
          "3000",
          "4000",
          "5000",
          "6000"
        ],
        "correct": 3
      },
      {
        "question": "నికానోర్ యూదులను ఏమి చేయాలనుకొనెను?",
        "options": [
          "స్నేహితులుగా చేయాలనుకొనెను",
          "చంపాలనుకొనెను",
          "బానిసలుగా ఉంచాలనుకొనెను",
          "అమ్మాలనుకొనెను"
        ],
        "correct": 3
      },
      {
        "question": "యూదా తన సైన్యమునకు ఎవరిని గూర్చి చెప్పెను?",
        "options": [
          "సొలొమోను",
          "దావీదు",
          "సౌలు",
          "సన్హెరీబు కాలంలో జరిగిన సహాయము"
        ],
        "correct": 3
      },
      {
        "question": "యూదులు శత్రువుల నుండి ఏమి పంచుకొనిరి?",
        "options": [
          "కొల్లసొమ్ము",
          "భూమి",
          "ఆయుధములు",
          "గుర్రములు"
        ],
        "correct": 0
      },
      {
        "question": "నికానోర్ ఎలా పారిపోయెను?",
        "options": [
          "సైన్యముతో",
          "రాజాలాంఛనములతో",
          "మారువేషములో ఒంటరిగా",
          "రథము మీద"
        ],
        "correct": 2
      }
    ],
    "9": [
      {
        "question": "అంతియొకస్ ఏ నగరము నుండి అవమానముతో వెనుదిరిగెను?",
        "options": [
          "రోమ్",
          "యెరూషలేము",
          "పెర్సెపోలిస్",
          "అలెగ్జాండ్రియా"
        ],
        "correct": 2
      },
      {
        "question": "అంతియొకస్ కు ఏ వ్యాధి వచ్చెను?",
        "options": [
          "కడుపులో భయంకరమైన నొప్పి",
          "జ్వరము",
          "గుడ్డితనము",
          "కుష్ఠు"
        ],
        "correct": 0
      },
      {
        "question": "అంతియొకస్ ఎవరికి లేఖ వ్రాసెను?",
        "options": [
          "తన కుమారునికి",
          "స్నేహితులకు",
          "రోమీయులకు",
          "యూదులకు"
        ],
        "correct": 3
      },
      {
        "question": "అంతియొకస్ మరణానంతరం ఎవరు రాజాయెను?",
        "options": [
          "అతని కుమారుడు అంతియొకస్ యూపటార్",
          "ఫిలిప్పు",
          "లైసియస్",
          "దెమేత్రియస్"
        ],
        "correct": 0
      },
      {
        "question": "అంతియొకస్ ఎక్కడ మరణించెను?",
        "options": [
          "యుద్ధరంగములో",
          "పర్వతములలో ప్రయాణములో",
          "రాజభవనములో",
          "యెరూషలేములో"
        ],
        "correct": 1
      }
    ],
    "10": [
      {
        "question": "యూదా మరియు అతని వారు దేనిని తిరిగి స్వాధీనపరచుకొనిరి?",
        "options": [
          "నగరమును మరియు దేవాలయమును",
          "సముద్ర తీరమును",
          "కోటను",
          "రాజభవనమును"
        ],
        "correct": 0
      },
      {
        "question": "దేవాలయ శుద్ధీకరణ పండుగను ఎన్ని రోజులు జరుపుకొనిరి?",
        "options": [
          "7",
          "12",
          "3",
          "8"
        ],
        "correct": 3
      },
      {
        "question": "తిమోతి ఎవరితో వచ్చి యుద్ధము చేసెను?",
        "options": [
          "యూదులతో",
          "రోమీయులతో",
          "అన్యజన సైన్యముతో",
          "గ్రీకులతో"
        ],
        "correct": 2
      },
      {
        "question": "యూదా సైన్యమునకు ఆకాశము నుండి ఎవరు సహాయము చేసిరి?",
        "options": [
          "మేఘములు",
          "ఐదుగురు రౌతులు",
          "దేవదూతలు",
          "పక్షులు"
        ],
        "correct": 1
      },
      {
        "question": "తిమోతి ఎక్కడ చంపబడెను?",
        "options": [
          "గజారా కోటలో",
          "గుహలో",
          "నదిలో",
          "యుద్ధరంగములో"
        ],
        "correct": 0
      }
    ],
    "11": [
      {
        "question": "లైసియస్ ఎంత సైన్యముతో వచ్చెను?",
        "options": [
          "80 వేలు",
          "1 లక్ష",
          "50 వేలు",
          "60 వేలు"
        ],
        "correct": 0
      },
      {
        "question": "యూదులకు ముందుగా ఎవరు నడిచిరి?",
        "options": [
          "యూదా",
          "తెల్లని వస్త్రములు ధరించిన గుర్రపు రౌతు",
          "యాజకుడు",
          "ధ్వజధారి"
        ],
        "correct": 1
      },
      {
        "question": "లైసియస్ ఓడిపోయిన తరువాత ఏమి చేసెను?",
        "options": [
          "తిరిగి యుద్ధము చేసెను",
          "సంధి చేసుకొనెను",
          "ఆత్మహత్య చేసుకొనెను",
          "పారిపోయెను"
        ],
        "correct": 1
      },
      {
        "question": "రాజు యూదులకు ఏమి అనుమతి ఇచ్చెను?",
        "options": [
          "వారి ధర్మశాస్త్రమును అనుసరించుటకు",
          "సైన్యమును ఉంచుకొనుటకు",
          "విదేశాలకు వెళ్ళుటకు",
          "పన్నులు కట్టకుండుటకు"
        ],
        "correct": 0
      },
      {
        "question": "రోమీయులు కూడా ఎవరికి లేఖ వ్రాసిరి?",
        "options": [
          "లైసియస్ కు",
          "అందరికీ",
          "యూదులకు",
          "రాజుకు"
        ],
        "correct": 2
      }
    ],
    "12": [
      {
        "question": "యొప్పా వారు యూదులను ఎలా చంపిరి?",
        "options": [
          "అగ్నితో",
          "కత్తితో",
          "సముద్రములో ముంచి",
          "రాళ్లతో"
        ],
        "correct": 2
      },
      {
        "question": "యూదా యొప్పా రేవును ఏమి చేసెను?",
        "options": [
          "శుభ్రము చేసెను",
          "తగులబెట్టెను",
          "స్వాధీనపరచుకొనెను",
          "విడిచిపెట్టెను"
        ],
        "correct": 1
      },
      {
        "question": "కర్నియోనులో యూదా ఎవరిని ఓడించెను?",
        "options": [
          "లైసియస్ ను",
          "గోర్గియస్ ను",
          "నికానోర్ ను",
          "తిమోతిని"
        ],
        "correct": 3
      },
      {
        "question": "చనిపోయిన యూదుల వస్త్రముల క్రింద ఏమి దొరికెను?",
        "options": [
          "లేఖలు",
          "ఆయుధములు",
          "బంగారము",
          "విగ్రహ సంబంధమైన తాయెత్తులు"
        ],
        "correct": 3
      },
      {
        "question": "యూదా వారి కొరకు ఏమి చేసెను?",
        "options": [
          "పాపపరిహార్థ బలి అర్పించెను",
          "ఏడ్చెను",
          "కోపగించెను",
          "విడిచిపెట్టెను"
        ],
        "correct": 0
      }
    ],
    "13": [
      {
        "question": "అంతియొకస్ యూపటార్ ఎవరితో కలిసి వచ్చెను?",
        "options": [
          "తిమోతి",
          "ఫిలిప్పు",
          "నికానోర్",
          "లైసియస్"
        ],
        "correct": 3
      },
      {
        "question": "మెనెలాస్ ఎలా చంపబడెను?",
        "options": [
          "కత్తితో",
          "ఉరితీసి",
          "రాళ్లతో కొట్టి",
          "బూడిద రాశిలో పడవేసి"
        ],
        "correct": 3
      },
      {
        "question": "యూదా మోదీనులో రాత్రివేళ ఏమి చేసెను?",
        "options": [
          "రాజు శిబిరముపై దాడి చేసెను",
          "పారిపోయెను",
          "నిద్రించెను",
          "ప్రార్థించెను"
        ],
        "correct": 0
      },
      {
        "question": "రాజు యూదులతో సంధి చేసుకొని తరువాత ఏమి చేసెను?",
        "options": [
          "బహుమానములు ఇచ్చెను",
          "మాట నిలబెట్టుకొనెను",
          "సీయోను కోట గోడను పడగొట్టెను",
          "వెళ్లిపోయెను"
        ],
        "correct": 2
      },
      {
        "question": "రాజు ఎవరిని ప్రధాన యాజకునిగా నియమించెను?",
        "options": [
          "ఎవరినీ కాదు",
          "అల్కిమస్",
          "యూదా",
          "ఓనియాస్"
        ],
        "correct": 1
      }
    ],
    "14": [
      {
        "question": "అల్కిమస్ ఎవరి యొద్దకు వెళ్ళెను?",
        "options": [
          "అంతియొకస్",
          "యూదా",
          "రోమీయులు",
          "దెమేత్రియస్"
        ],
        "correct": 3
      },
      {
        "question": "రాజు ఎవరిని యూదయకు పంపెను?",
        "options": [
          "గోర్గియస్",
          "తిమోతి",
          "నికానోర్",
          "లైసియస్"
        ],
        "correct": 2
      },
      {
        "question": "నికానోర్ మొదట యూదాతో ఎలా ఉండెను?",
        "options": [
          "శత్రువుగా",
          "స్నేహితునిగా",
          "భయముతో",
          "దూరముగా"
        ],
        "correct": 1
      },
      {
        "question": "రాజీస్ అనే వృద్ధుడు ఏమి చేసెను?",
        "options": [
          "యుద్ధము చేసెను",
          "శత్రువులకు చిక్కకుండ ఆత్మహత్య చేసుకొనెను",
          "లొంగిపోయెను",
          "పారిపోయెను"
        ],
        "correct": 1
      },
      {
        "question": "నికానోర్ దేవాలయమును గూర్చి ఏమి బెదిరించెను?",
        "options": [
          "పడగొట్టి దానికి బదులు ద్యోనుష్యుని గుడి కట్టెదనని",
          "కాల్చివేసెదనని",
          "కొల్లగొట్టెదనని",
          "మూసివేసెదనని"
        ],
        "correct": 0
      }
    ],
    "15": [
      {
        "question": "నికానోర్ ఏ రోజున యూదులపై దాడి చేయాలనుకొనెను?",
        "options": [
          "పస్కా పండుగన",
          "అమావాస్య నాడు",
          "విశ్రాంతి దినమున",
          "సాధారణ దినమున"
        ],
        "correct": 2
      },
      {
        "question": "యూదాకు దర్శనములో ఎవరు కనబడిరి?",
        "options": [
          "దావీదు మరియు సొలొమోను",
          "మోషే మరియు ఏలీయా",
          "ఓనియాస్ మరియు యిర్మీయా",
          "అబ్రాహాము మరియు ఇస్సాకు"
        ],
        "correct": 2
      },
      {
        "question": "యిర్మీయా యూదాకు ఏమి ఇచ్చెను?",
        "options": [
          "గ్రంథము",
          "బంగారు కత్తి",
          "డాలు",
          "కిరీటము"
        ],
        "correct": 1
      },
      {
        "question": "యుద్ధములో ఎవరు ఓడిపోయిరి?",
        "options": [
          "నికానోర్ సైన్యము",
          "రోమీయులు",
          "ఎవరూ కాదు",
          "యూదులు"
        ],
        "correct": 0
      },
      {
        "question": "యూదులు నికానోర్ తల మరియు చెయ్యిని ఎక్కడ వేలాడదీసిరి?",
        "options": [
          "నగర ద్వారమున",
          "యుద్ధభూమిలో",
          "యెరూషలేము ప్రాకారము మీద",
          "దేవాలయములో"
        ],
        "correct": 2
      }
    ]
  },
  "bookName": "2 Maccabees"
}