{
  "chapters": 4,
  "levels": {
    "1": [
      {
        "question": "దేవుడు మనకు పిరికితనము గల ఆత్మను ఇయ్యలేదు, మరి ఎట్టి ఆత్మను ఇచ్చెను?",
        "options": [
          "నిరాశ గల ఆత్మను",
          "శక్తియు ప్రేమయు ఇంద్రియ నిగ్రహమును గల ఆత్మనే",
          "భయమును గల ఆత్మను",
          "అవిశ్వాసపు ఆత్మను"
        ],
        "correct": 1
      },
      {
        "question": "నీ యందున్న ఎట్టి విశ్వాసము నాకు జ్ఞాపకము వచ్చుచున్నది?",
        "options": [
          "సాధారణ విశ్వాసము",
          "చంచలమైన విశ్వాసము",
          "అల్ప విశ్వాసము",
          "నిష్కపటమైన విశ్వాసము"
        ],
        "correct": 3
      },
      {
        "question": "నేను నమ్మినవానిని ఎరుగుదును, ఆయన నేను ఆయనకు అప్పగించిన దానిని కాపాడుటకు...",
        "options": [
          "మరచిపోవును",
          "విడిచిపెట్టును",
          "శక్తుడై ఉన్నాడని రూఢిగా నమ్ముచున్నాను",
          "అశక్తుడై ఉన్నాడు"
        ],
        "correct": 2
      },
      {
        "question": "ప్రభువు ఆ దినమందు ఎవరిని కరుణించును గాక?",
        "options": [
          "ఒనేసిపొరు ఇంటివారిని",
          "దేమాను",
          "అలెకాండరును",
          "ఫైజెల్లను"
        ],
        "correct": 0
      },
      {
        "question": "ఆసియాలో ఉన్నవారందరు నన్ను...",
        "options": [
          "కాపాడిరి",
          "చేరదీసిరి",
          "సన్మానించిరి",
          "విడిచిపోయిరి"
        ],
        "correct": 3
      }
    ],
    "2": [
      {
        "question": "క్రీస్తు యేసు యొక్క మంచి సైనికుని వలె నీవు దేనిని అనుభవించుము?",
        "options": [
          "శ్రమను",
          "ధనమును",
          "భోగములను",
          "సుఖమును"
        ],
        "correct": 0
      },
      {
        "question": "పందెములో పోరాడువాడు నియమప్రకారము పోరాడకపోతే వానికి ఏమి దొరకదు?",
        "options": [
          "శిక్ష",
          "తిండి",
          "కిరీటము (బహుమానము)",
          "అవమానము"
        ],
        "correct": 2
      },
      {
        "question": "దేవుని వాక్యము...",
        "options": [
          "దాచబడినది",
          "బంధింపబడియుండలేదు",
          "బంధింపబడినది",
          "నశింపబడినది"
        ],
        "correct": 1
      },
      {
        "question": "సత్య వాక్యమును సరిగా ఉపదేశించువానిగా నిన్ను నీవే దేవునికి ఎలా కనుపరచుకొనుము?",
        "options": [
          "జ్ఞానిగా",
          "యోగ్యునిగా",
          "అయోగ్యునిగా",
          "సోమరిగా"
        ],
        "correct": 1
      },
      {
        "question": "గొప్ప ఇంటిలో వెండివియు బంగారువియు మాత్రమే గాక, ఇంకా ఎట్టి పాత్రలుండును?",
        "options": [
          "రాతివి",
          "ఇనుపవి",
          "రాగివి",
          "కర్రవియు మంటివియు"
        ],
        "correct": 3
      }
    ],
    "3": [
      {
        "question": "అంత్య దినములలో ఎట్టి కాలములు వచ్చునని తెలుసుకొనుము?",
        "options": [
          "శాంతి కాలములు",
          "సంతోష కాలములు",
          "అపాయకరమైన కాలములు",
          "మంచి కాలములు"
        ],
        "correct": 2
      },
      {
        "question": "మనుష్యులు స్వార్థప్రియులును ధనాపేక్షకులునై యుండి, పైకి భక్తి గలవారివలె ఉండియు, దేనిని విసర్జించుదురు?",
        "options": [
          "భక్తి శక్తిని",
          "ధనమును",
          "కీర్తిని",
          "లోకమును"
        ],
        "correct": 0
      },
      {
        "question": "దైవజనుడు సన్నద్ధుడై యుండునట్లు దైవావేశము వలన కలిగిన ప్రతి లేఖనము దేనికి లాభకరమై యున్నది?",
        "options": [
          "ధనార్జనకు",
          "వినోదమునకు",
          "కాలక్షేపమునకు",
          "ఉపదేశించుటకును, ఖండించుటకును, తప్పు దిద్దుటకును, శిక్షించుటకును"
        ],
        "correct": 3
      },
      {
        "question": "క్రీస్తు యేసు నందు సద్భక్తితో బ్రతుకనుద్దేశించువారందరు ఏమి పొందుదురు?",
        "options": [
          "హింస",
          "ధనము",
          "గౌరవము",
          "సుఖము"
        ],
        "correct": 0
      },
      {
        "question": "క్రీస్తు యేసు నందుంచవలసిన విశ్వాసము ద్వారా రక్షణార్థమైన జ్ఞానమును నీకు కలిగించుటకు శక్తి గలవి ఏవి?",
        "options": [
          "లోక జ్ఞానము",
          "వార్తాపత్రికలు",
          "పరిశుద్ధ లేఖనములు",
          "కథలు"
        ],
        "correct": 2
      }
    ],
    "4": [
      {
        "question": "వాక్యమును ప్రకటించుము; ఎప్పుడు ప్రయాసపడుము?",
        "options": [
          "వీలున్నప్పుడు",
          "సమయమందును అసమయమందును",
          "ఆదివారము మాత్రమే",
          "పండుగ దినములలో"
        ],
        "correct": 1
      },
      {
        "question": "నేను మంచి పోరాటము పోరాడితిని, నా పరుగు కడముట్టించితిని, ... కాపాడుకొంటిని.",
        "options": [
          "ప్రాణమును",
          "విశ్వాసమును",
          "ధనమును",
          "గౌరవమును"
        ],
        "correct": 1
      },
      {
        "question": "ఇక మీదట నా కొరకు ఏమి ఉంచబడియున్నది?",
        "options": [
          "శిక్ష",
          "బంగారు గొలుసు",
          "కొత్త వస్త్రములు",
          "నీతి కిరీటము"
        ],
        "correct": 3
      },
      {
        "question": "దేమా ఇహలోకమును ప్రేమించి నన్ను విడిచి ఎక్కడికి వెళ్ళెను?",
        "options": [
          "దాల్మతియకు",
          "రోముకు",
          "థెస్సలొనీకకు",
          "గలతీయకు"
        ],
        "correct": 2
      },
      {
        "question": "నాతో కూడా ఎవరైనను నిలువలేదు, అందరు నన్ను విడిచిపోయిరి. అయితే నన్ను బలపరచినది ఎవరు?",
        "options": [
          "ప్రభువు",
          "రాజు",
          "న్యాయాధిపతి",
          "స్నేహితుడు"
        ],
        "correct": 0
      }
    ]
  },
  "bookName": "2 Timothy"
}